data/__init__.py
data/node_control.conf
data/nssm_original.exe
data/migrations/README.md
data/migrations/__init__.py
data/migrations/deb/1_0_96_to_1_0_97.py
data/migrations/deb/1_1_150_to_1_1_151.py
data/migrations/deb/1_2_188_to_1_2_189.py
data/migrations/deb/1_2_233_to_1_2_234.py
data/migrations/deb/1_2_273_to_1_2_274.py
data/migrations/deb/1_3_396_to_1_3_397.py
data/migrations/deb/1_3_428_to_1_3_429.py
data/migrations/deb/1_3_433_to_1_3_434.py
data/migrations/deb/1_4_500_to_1_4_501.py
data/migrations/deb/1_6_703_to_1_6_704.py
data/migrations/deb/1_9_1_to_1_9_2.py
data/migrations/deb/__init__.py
data/migrations/deb/disabled_1_0_97_to_1_0_96.py
data/migrations/deb/helper_1_0_96_to_1_0_97.py
home/runner/.indy/nssm_original.exe
indy_common/__init__.py
indy_common/auth.py
indy_common/compat_set.py
indy_common/config.py
indy_common/config_helper.py
indy_common/config_util.py
indy_common/constants.py
indy_common/did_method.py
indy_common/exceptions.py
indy_common/generates_request.py
indy_common/identity.py
indy_common/init_util.py
indy_common/node_version.py
indy_common/node_version_fallback.py
indy_common/req_utils.py
indy_common/roles.py
indy_common/serialization.py
indy_common/setup_util.py
indy_common/strict_types.py
indy_common/transactions.py
indy_common/txn_util.py
indy_common/types.py
indy_common/util.py
indy_common/version.py
indy_common/authorize/__init__.py
indy_common/authorize/auth_actions.py
indy_common/authorize/auth_cons_strategies.py
indy_common/authorize/auth_constraints.py
indy_common/authorize/auth_map.py
indy_common/authorize/auth_request_validator.py
indy_common/authorize/authorizer.py
indy_common/authorize/helper.py
indy_common/migration/__init__.py
indy_common/migration/helper.py
indy_common/pool/__init__.py
indy_common/pool/pool.py
indy_common/state/__init__.py
indy_common/state/config.py
indy_common/state/domain.py
indy_common/state/state_constants.py
indy_common/test/__init__.py
indy_common/test/__main__.py
indy_common/test/conftest.py
indy_node-1.13.2.dist-info/LICENSE
indy_node-1.13.2.dist-info/METADATA
indy_node-1.13.2.dist-info/WHEEL
indy_node-1.13.2.dist-info/top_level.txt
indy_node-1.13.2.dist-info/RECORD
